AUTHORS
CHANGES
LICENSE
MANIFEST.in
README.rst
setup.py
docs/Makefile
docs/changes.rst
docs/cmdline.rst
docs/conf.py
docs/config_files.rst
docs/features.rst
docs/index.rst
docs/make.bat
docs/quickstart.rst
docs/_themes/nature2/layout.html
docs/_themes/nature2/theme.conf
docs/_themes/nature2/static/nature2.css
docs/_themes/pyg/theme.conf
docs/_themes/pyg/static/pyg.css_t
docs/cmdline/inst_uninst.rst
docs/cmdline/minor_cmd.rst
docs/cmdline/req_bund.rst
docs/cmdline/upgr_down_shell.rst
pyg/__init__.py
pyg/core.py
pyg/freeze.py
pyg/inst.py
pyg/locations.py
pyg/log.py
pyg/pack.py
pyg/req.py
pyg/scripts.py
pyg/utils.py
pyg/web.py
pyg.egg-info/PKG-INFO
pyg.egg-info/SOURCES.txt
pyg.egg-info/dependency_links.txt
pyg.egg-info/entry_points.txt
pyg.egg-info/not-zip-safe
pyg.egg-info/requires.txt
pyg.egg-info/top_level.txt
pyg/parser/__init__.py
pyg/parser/_opts.py
pyg/parser/formatter.py
pyg/parser/parser.py
pyg/parser/shell.py
pyg/vcs/__init__.py
pyg/vcs/base.py
pyg/vcs/gist.py
pyg/vcs/vcs.py
tests/README.txt
tests/pypi_cache_server.py
tests/run.py
tests/test26.py
tests/features/check.feature
tests/features/help.feature
tests/features/install.feature
tests/features/remove.feature
tests/features/search.feature
tests/features/steps.py
tests/features/test_errors.feature