Metadata-Version: 1.1
Name: pyg
Version: 1.0
Summary: Python Package Manager
Home-page: http://pyg.readthedocs.org/
Author: Michele Lacchia
Author-email: michelelacchia@gmail.com
License: MIT
Download-URL: http://pypi.python.org/pypi/pyg
Keywords: python,easy_install,pip,setuptools,package manager,command line,CLI
Platform: any
Classifier: Development Status :: 4 - Beta
Classifier: Intended Audience :: Developers
Classifier: License :: OSI Approved :: MIT License
Classifier: Programming Language :: Python :: 2.6
Classifier: Programming Language :: Python :: 2.7
Classifier: Topic :: Software Development :: Build Tools
Provides: pyg
